sdkboil/__init__.py
sdkboil/action.py
sdkboil/apicontext.py
sdkboil/exception.py
sdkboil/object.py
sdkboil/test.py
tinabasdk/__init__.py
tinabasdk/actions.py
tinabasdk/apicontext.py
tinabasdk/callbacks.py
tinabasdk/exceptions.py
tinabasdk/objects.py
tinaba_pay_sdk-1.2.1.dist-info/LICENCE
tinaba_pay_sdk-1.2.1.dist-info/METADATA
tinaba_pay_sdk-1.2.1.dist-info/WHEEL
tinaba_pay_sdk-1.2.1.dist-info/top_level.txt
tinaba_pay_sdk-1.2.1.dist-info/RECORD
